ml_clerk/__init__.py
ml_clerk/clerk.py
ml_clerk-1.0.0.dist-info/LICENSE
ml_clerk-1.0.0.dist-info/METADATA
ml_clerk-1.0.0.dist-info/WHEEL
ml_clerk-1.0.0.dist-info/top_level.txt
ml_clerk-1.0.0.dist-info/RECORD
