Metadata-Version: 2.1
Name: ml-clerk
Version: 1.0.0
Summary: Module to record/document your model changes
Home-page: https://github.com/unkush-garg/ml-clerk
Author: Ankush Garg
Author-email: unkushgarg@gmail.com
License: UNKNOWN
Platform: UNKNOWN
License-File: LICENSE
Requires-Dist: numpy (==1.22.3)
Requires-Dist: pandas (==1.4.2)
Requires-Dist: pygsheets (==2.0.5)
Requires-Dist: python-dotenv (==0.20.0)
Requires-Dist: openpyxl (==3.0.9)
